jz3/__init__.py
jz3/analysis/__init__.py
jz3/analysis/archive/__init__.py
jz3/analysis/archive/display_results.ipynb
jz3/analysis/archive/export_to_excel.py
jz3/analysis/archive/test.xlsx
jz3/analysis/images/distinct_5s_cap.png
jz3/analysis/images/distinct_extended.png
jz3/analysis/images/extended_time_comparison.png
jz3/analysis/images/limited_comparison.png
jz3/analysis/images/whole_distinct_5s_cap.png
jz3/analysis/images/whole_distinct_extended.png
jz3/analysis/scripts/__init__.py
jz3/analysis/scripts/compare_whole_problems.py
jz3/analysis/scripts/plot_comparison.py
jz3/solvers/__init__.py
jz3/solvers/cvc5-macOS-arm64
jz3/src/SMTs/SMTs.py
jz3/src/SMTs/__init__.py
jz3/src/__init__.py
jz3/src/conditional_constraints.smt2
jz3/src/config.py
jz3/src/garbage_smt.smt2
jz3/src/run_solvers.py
jz3/src/smt_file.smt2
jz3/src/z3_quick_start_guide.py
jz3/src/z3_wrapper.py
jz3/tests/__init__.py
jz3/tests/test_solver.py
jz3/utils/__init__.py
jz3/utils/helpers.py
jz3-0.1.13.dist-info/LICENSE-Z3.txt
jz3-0.1.13.dist-info/LICENSE.txt
jz3-0.1.13.dist-info/METADATA
jz3-0.1.13.dist-info/WHEEL
jz3-0.1.13.dist-info/RECORD
