Metadata-Version: 2.1
Name: jz3
Version: 0.1.13
Summary: A library for benchmarking difference smt sovlers
Home-page: https://github.com/Robert-Jia00129/jz3
License: MIT
Author: Sebastiaan Joosten
Requires-Python: >=3.11
Classifier: Development Status :: 3 - Alpha
Classifier: Intended Audience :: Developers
Classifier: License :: OSI Approved :: MIT License
Classifier: Programming Language :: Python :: 3
Classifier: Programming Language :: Python :: 3.11
Classifier: Programming Language :: Python :: 3.12
Classifier: Programming Language :: Python :: 3.13
Classifier: Programming Language :: Python :: 3.8
Classifier: Topic :: Software Development :: Libraries
Requires-Dist: matplotlib
Requires-Dist: z3-solver
Project-URL: Source Code, https://github.com/Robert-Jia00129/jz3
